agenticmesh/__init__.py
mcp_server_mesh-0.0.9.dist-info/LICENSE
mcp_server_mesh-0.0.9.dist-info/METADATA
mcp_server_mesh-0.0.9.dist-info/WHEEL
mcp_server_mesh-0.0.9.dist-info/RECORD
