Metadata-Version: 2.3
Name: mcp-server-mesh
Version: 0.0.9
Summary: MCP Orchestration Framework for Multi-Agent and Micro-Agent
Author: eric-epsilla
Author-email: eric@epsilla.com
Requires-Python: >=3.10,<4.0
Classifier: Programming Language :: Python :: 3
Classifier: Programming Language :: Python :: 3.10
Classifier: Programming Language :: Python :: 3.11
Classifier: Programming Language :: Python :: 3.12
Classifier: Programming Language :: Python :: 3.13
Requires-Dist: pyepsilla (>=0.3.14,<0.4.0)
